MANIFEST.in
README.rst
setup.cfg
setup.py
versioneer.py
aiomeasures/__init__.py
aiomeasures/_version.py
aiomeasures/checks.py
aiomeasures/collectors.py
aiomeasures/events.py
aiomeasures/metrics.py
aiomeasures/util.py
aiomeasures/clients/__init__.py
aiomeasures/clients/bases.py
aiomeasures/clients/datadog/__init__.py
aiomeasures/clients/datadog/client.py
aiomeasures/clients/datadog/formatting.py
aiomeasures/clients/statsd/__init__.py
aiomeasures/clients/statsd/client.py
aiomeasures/clients/statsd/formatting.py
aiomeasures/reporters/__init__.py
aiomeasures/reporters/statsd_reporter.py
aiomeasures_fork.egg-info/PKG-INFO
aiomeasures_fork.egg-info/SOURCES.txt
aiomeasures_fork.egg-info/dependency_links.txt
aiomeasures_fork.egg-info/requires.txt
aiomeasures_fork.egg-info/top_level.txt