Metadata-Version: 1.1
Name: aiomeasures-fork
Version: 0.5.16
Summary: Collect and send metrics to StatsD
Home-page: http://lab.errorist.xyz/abc/
Author: Xavier Barbosa
Author-email: clint.northwood@gmail.com
License: MIT
Platform: UNKNOWN
Classifier: Development Status :: 5 - Production/Stable
Classifier: Intended Audience :: Developers
Classifier: License :: OSI Approved :: MIT License
Classifier: Operating System :: OS Independent
Classifier: Programming Language :: Python :: 3
Classifier: Programming Language :: Python :: 3.3
Classifier: Programming Language :: Python :: 3.4
Classifier: Programming Language :: Python :: 3.5
Classifier: Topic :: Software Development :: Libraries
Classifier: Topic :: Software Development :: Libraries :: Python Modules
